maryjane.py
maryjane-4.4.7.dist-info/DESCRIPTION.rst
maryjane-4.4.7.dist-info/METADATA
maryjane-4.4.7.dist-info/RECORD
maryjane-4.4.7.dist-info/WHEEL
maryjane-4.4.7.dist-info/entry_points.txt
maryjane-4.4.7.dist-info/metadata.json
maryjane-4.4.7.dist-info/top_level.txt
