Metadata-Version: 2.0
Name: maryjane
Version: 4.4.7
Summary: Python file watcher and task manager
Home-page: http://github.com/pylover/maryjane
Author: Vahid Mardani
Author-email: vahid.mardani@gmail.com
License: WTFPL
Platform: UNKNOWN
Classifier: Environment :: Console
Classifier: Intended Audience :: Developers
Classifier: Natural Language :: English
Classifier: Development Status :: 4 - Beta
Classifier: License :: Other/Proprietary License
Classifier: Operating System :: OS Independent
Classifier: Programming Language :: Python :: 3.6
Classifier: Topic :: Software Development
Classifier: Topic :: Utilities
Requires-Dist: watchdog
